helenservice/__init__.py
helenservice/api_client.py
helenservice/api_exceptions.py
helenservice/api_response.py
helenservice/cli.py
helenservice/const.py
helenservice/helen_session.py
helenservice/price_client.py
helenservice/utils.py
oma_helen_cli-1.5.0.dist-info/LICENSE
oma_helen_cli-1.5.0.dist-info/METADATA
oma_helen_cli-1.5.0.dist-info/WHEEL
oma_helen_cli-1.5.0.dist-info/entry_points.txt
oma_helen_cli-1.5.0.dist-info/top_level.txt
oma_helen_cli-1.5.0.dist-info/RECORD
