Metadata-Version: 2.1
Name: oma-helen-cli
Version: 1.5.0
Summary: Oma Helen API library and CLI
Author-email: carohauta <carosoft.dev@gmail.com>
License: MIT
Project-URL: Homepage, https://github.com/carohauta/oma-helen-cli
Project-URL: Repository, https://github.com/carohauta/oma-helen-cli
Project-URL: Issues, https://github.com/carohauta/oma-helen-cli/issues
Keywords: helen,electricity,api,cli,finland
Classifier: Development Status :: 5 - Production/Stable
Classifier: Intended Audience :: Developers
Classifier: Intended Audience :: End Users/Desktop
Classifier: Natural Language :: English
Classifier: Programming Language :: Python :: 3
Classifier: Programming Language :: Python :: 3.9
Classifier: Programming Language :: Python :: 3.10
Classifier: Programming Language :: Python :: 3.11
Classifier: Programming Language :: Python :: 3.12
Classifier: Operating System :: OS Independent
Classifier: Topic :: Utilities
Classifier: Topic :: Internet :: WWW/HTTP :: Dynamic Content
Requires-Python: >=3.9
License-File: LICENSE
Requires-Dist: beautifulsoup4==4.12.3
Requires-Dist: python-dateutil==2.9.0.post0
Requires-Dist: requests>=2.28.1
Requires-Dist: soupsieve==2.5
Requires-Dist: urllib3>=1.26.5
Requires-Dist: cachetools>=5.3.3
Provides-Extra: test
Requires-Dist: pytest>=7.0.0; extra == "test"
Requires-Dist: pytest-mock>=3.0.0; extra == "test"
